objectit_airflow_monitoring/Slack.py
objectit_airflow_monitoring/__init__.py
objectit_airflow_monitoring/test_slack.py
objectit_airflow_monitoring-0.0.5.dist-info/LICENSE
objectit_airflow_monitoring-0.0.5.dist-info/METADATA
objectit_airflow_monitoring-0.0.5.dist-info/WHEEL
objectit_airflow_monitoring-0.0.5.dist-info/top_level.txt
objectit_airflow_monitoring-0.0.5.dist-info/RECORD
